README.rst
setup.cfg
setup.py
echo_api/__init__.py
echo_api/api.py
echo_api/tests.py
echo_api/wrappers.py
echo_api.egg-info/PKG-INFO
echo_api.egg-info/SOURCES.txt
echo_api.egg-info/dependency_links.txt
echo_api.egg-info/requires.txt
echo_api.egg-info/top_level.txt