Metadata-Version: 1.2
Name: echo-api
Version: 1.0.5.dev0
Summary: Python API for Echo credentialing software
Home-page: https://github.com/jjorissen52/echo_api
Author: John-Paul Jorissen
Author-email: jjorissen52@gmail.com
License: Apache
Keywords: ECHO Python API SOAP
Platform: UNKNOWN
Classifier: Development Status :: 3 - Alpha
Classifier: Intended Audience :: Developers
Classifier: Programming Language :: Python :: 3.6
Classifier: Operating System :: Microsoft :: Windows :: Windows 10
Classifier: Operating System :: POSIX :: Linux
Classifier: Topic :: Office/Business
Classifier: License :: OSI Approved :: Apache Software License
Classifier: Programming Language :: Python :: 3.5
Requires-Python: >=3.4
